.gitignore
.readthedocs.yml
CHANGES.rst
CITATION.cff
LICENSE
MANIFEST.in
README.rst
pyproject.toml
setup.py
tox.ini
.github/workflows/draft-pdf.yml
.github/workflows/tox-tests.yml
docs/Makefile
docs/conf.py
docs/index.rst
docs/make.bat
docs/dust_extinction/choose_model.rst
docs/dust_extinction/dev_model.rst
docs/dust_extinction/extinction.rst
docs/dust_extinction/extinguish.rst
docs/dust_extinction/fit_extinction.rst
docs/dust_extinction/install.rst
docs/dust_extinction/model_flavors.rst
docs/dust_extinction/reference_api.rst
docs/dust_extinction/references.rst
docs/logo/logo.odg
docs/logo/logo.png
dust_extinction/__init__.py
dust_extinction/averages.py
dust_extinction/baseclasses.py
dust_extinction/conftest.py
dust_extinction/conversions.py
dust_extinction/grain_models.py
dust_extinction/helpers.py
dust_extinction/parameter_averages.py
dust_extinction/shapes.py
dust_extinction/version.py
dust_extinction/warnings.py
dust_extinction.egg-info/PKG-INFO
dust_extinction.egg-info/SOURCES.txt
dust_extinction.egg-info/dependency_links.txt
dust_extinction.egg-info/not-zip-safe
dust_extinction.egg-info/requires.txt
dust_extinction.egg-info/top_level.txt
dust_extinction/data/C25_M31Ave.dat
dust_extinction/data/CT06_pixiedust.dat
dust_extinction/data/D22.dat
dust_extinction/data/D22_Rv_slope.dat
dust_extinction/data/EXT_C11.RES.dat
dust_extinction/data/EXT_DBP90.RES.dat
dust_extinction/data/EXT_J13.RES.dat
dust_extinction/data/F19_tabulated.dat
dust_extinction/data/G21_IRS.dat
dust_extinction/data/G21_IRS_fullres.dat
dust_extinction/data/G21_PHOT.dat
dust_extinction/data/G24_SMCAvg.dat
dust_extinction/data/G24_SMCBumps.dat
dust_extinction/data/G25_M33Ave.dat
dust_extinction/data/GCC09_FUSE.dat
dust_extinction/data/GCC09_IUE.dat
dust_extinction/data/GCC09_PHOT.dat
dust_extinction/data/README.rst
dust_extinction/data/THEMIS_2.0_EXT_2.RES.txt
dust_extinction/data/astrodust+PAH_MW_RV3.1.fits
dust_extinction/data/fritz11_galcenter.dat
dust_extinction/data/kext_albedo_WD_LMC2_10.dat
dust_extinction/data/kext_albedo_WD_LMCavg_20.dat
dust_extinction/data/kext_albedo_WD_MW_3.1_60.dat
dust_extinction/data/kext_albedo_WD_MW_3.1_60_D03.dat
dust_extinction/data/kext_albedo_WD_MW_4.0A_40_D03.dat
