Metadata-Version: 2.4
Name: dust_extinction
Version: 1.6
Summary: Interstellar Dust Extinction Models
Author-email: "Karl D. Gordon" <kgordon@stsci.edu>
License: BSD 3-Clause License
Project-URL: repository, https://github.com/karllark/dust_extinction
Requires-Python: >=3.10
License-File: LICENSE
Requires-Dist: astropy
Requires-Dist: scipy
Provides-Extra: test
Requires-Dist: pytest; extra == "test"
Requires-Dist: pytest-doctestplus; extra == "test"
Requires-Dist: pytest-cov; extra == "test"
Requires-Dist: matplotlib; extra == "test"
Provides-Extra: docs
Requires-Dist: sphinx; extra == "docs"
Requires-Dist: sphinx-automodapi; extra == "docs"
Requires-Dist: matplotlib; extra == "docs"
Requires-Dist: graphviz; extra == "docs"
Dynamic: license-file
